mybox/__init__.py
mybox/compute.py
mybox/config.py
mybox/configparser.py
mybox/driver.py
mybox/filters.py
mybox/main.py
mybox/manager.py
mybox/package/__init__.py
mybox/package/base.py
mybox/package/brew_repo.py
mybox/package/clone.py
mybox/package/daemon.py
mybox/package/destination.py
mybox/package/flatpak.py
mybox/package/installer/__init__.py
mybox/package/installer/apt.py
mybox/package/installer/base.py
mybox/package/installer/brew.py
mybox/package/installer/dnf.py
mybox/package/installer/flatpak.py
mybox/package/links.py
mybox/package/manual_version.py
mybox/package/npm.py
mybox/package/shell.py
mybox/package/system.py
mybox/package/yum_repo.py
mybox/parallel.py
mybox/state/__init__.py
mybox/state/base.py
mybox/state/db.py
mybox/state/installed.py
mybox/state/version.py
mybox/tracker.py
mybox/utils.py
mybox-5.4.9.dist-info/METADATA
mybox-5.4.9.dist-info/WHEEL
mybox-5.4.9.dist-info/entry_points.txt
mybox-5.4.9.dist-info/licenses/LICENSE.md
mybox-5.4.9.dist-info/RECORD
