Metadata-Version: 2.4
Name: mybox
Version: 5.4.9
Summary: Manage the configuration and tools on your workstation without bothering the OS too much
License: GPL-3.0-or-later
License-File: LICENSE.md
Author: Alexey Kotlyarov
Author-email: a@koterpillar.com
Requires-Python: >=3.11,<4.0
Classifier: License :: OSI Approved :: GNU General Public License v3 or later (GPLv3+)
Classifier: Programming Language :: Python :: 3
Classifier: Programming Language :: Python :: 3.11
Classifier: Programming Language :: Python :: 3.12
Classifier: Programming Language :: Python :: 3.13
Classifier: Programming Language :: Python :: 3.14
Requires-Dist: PyYAML (>=6.0.3,<7.0.0)
Requires-Dist: alive-progress (>=3.3.0,<4.0.0)
Requires-Dist: beautifulsoup4 (>=4.14.2,<5.0.0)
Requires-Dist: httpx (>=0.28.1,<0.29.0)
Requires-Dist: jsonpath-ng (>=1.7.0,<2.0.0)
Requires-Dist: pydantic (>=2.11.9,<3.0.0)
Requires-Dist: trio (>=0.31.0,<0.32.0)
Requires-Dist: typed-argparse (>=0.3.1,<0.4.0)
Project-URL: Repository, https://github.com/koterpillar/mybox
